superstars/__init__.py
superstar-0.1.dist-info/LICENSE
superstar-0.1.dist-info/METADATA
superstar-0.1.dist-info/WHEEL
superstar-0.1.dist-info/top_level.txt
superstar-0.1.dist-info/RECORD
