Metadata-Version: 2.1
Name: superstar
Version: 0.1
Summary: Generating bollywood star names
Home-page: https://github.com/Aniket762/superstar
Author: Aniket Pal
Author-email: aniketindian8@gmail.com
License: UNKNOWN
Platform: UNKNOWN
Classifier: Programming Language :: Python :: 3
Classifier: License :: OSI Approved :: MIT License
Classifier: Operating System :: OS Independent
